pydantic_scim2/__init__.py
pydantic_scim2/base.py
pydantic_scim2/rfc7643/__init__.py
pydantic_scim2/rfc7643/enterprise_user.py
pydantic_scim2/rfc7643/group.py
pydantic_scim2/rfc7643/resource.py
pydantic_scim2/rfc7643/resource_type.py
pydantic_scim2/rfc7643/schema.py
pydantic_scim2/rfc7643/service_provider.py
pydantic_scim2/rfc7643/user.py
pydantic_scim2/rfc7644/__init__.py
pydantic_scim2/rfc7644/bulk.py
pydantic_scim2/rfc7644/error.py
pydantic_scim2/rfc7644/list_response.py
pydantic_scim2/rfc7644/patch_op.py
pydantic_scim2/rfc7644/search_request.py
pydantic_scim2-0.2.2.dist-info/LICENSE
pydantic_scim2-0.2.2.dist-info/METADATA
pydantic_scim2-0.2.2.dist-info/WHEEL
pydantic_scim2-0.2.2.dist-info/RECORD
