Metadata-Version: 2.1
Name: pydantic-scim2
Version: 0.2.2
Summary: SCIM2 models for pydantic
Home-page: https://github.com/yaal-coop/pydantic-scim2
License: Apache
Keywords: scim,scim2,provisioning,pydantic
Author: Yaal Coop
Author-email: contact@yaal.coop
Requires-Python: >=3.9,<4.0
Classifier: Development Status :: 3 - Alpha
Classifier: Environment :: Web Environment
Classifier: Intended Audience :: Developers
Classifier: License :: OSI Approved :: MIT License
Classifier: License :: Other/Proprietary License
Classifier: Operating System :: OS Independent
Classifier: Programming Language :: Python
Classifier: Programming Language :: Python :: 3
Classifier: Programming Language :: Python :: 3.9
Classifier: Programming Language :: Python :: 3.10
Classifier: Programming Language :: Python :: 3.11
Classifier: Programming Language :: Python :: 3.12
Classifier: Programming Language :: Python :: Implementation :: CPython
Requires-Dist: pydantic[email] (>=2.3.0,<3.0.0)
Project-URL: Documentation, https://pydantic-scim2.readthedocs.io
Project-URL: Repository, https://github.com/yaal-coop/pydantic-scim2
